[{"inputs":[{"internalType":"address","name":"target","type":"address"},{"internalType":"bytes4","name":"selector","type":"bytes4"},{"internalType":"uint256","name":"accountOffset","type":"uint256"},{"internalType":"bytes","name":"reason","type":"bytes"}],"name":"AssertionStaticCallFailed","type":"error"},{"inputs":[{"internalType":"uint256","name":"offset","type":"uint256"},{"internalType":"uint256","name":"dataLength","type":"uint256"}],"name":"InvalidAssertionAccountOffset","type":"error"},{"inputs":[{"internalType":"uint256","name":"dataLength","type":"uint256"}],"name":"InvalidAssertionCallData","type":"error"},{"inputs":[{"internalType":"uint256","name":"offset","type":"uint256"},{"internalType":"uint256","name":"returnDataLength","type":"uint256"}],"name":"InvalidAssertionReturnOffset","type":"error"},{"inputs":[{"internalType":"address","name":"target","type":"address"}],"name":"InvalidAssertionTarget","type":"error"},{"inputs":[{"internalType":"address","name":"target","type":"address"},{"internalType":"bytes4","name":"selector","type":"bytes4"},{"internalType":"uint256","name":"accountOffset","type":"uint256"},{"internalType":"uint256","name":"returnOffset","type":"uint256"},{"internalType":"uint256","name":"actual","type":"uint256"},{"internalType":"uint256","name":"maximum","type":"uint256"}],"name":"StaticCallUint256AboveMaximum","type":"error"},{"inputs":[{"internalType":"address","name":"target","type":"address"},{"internalType":"bytes4","name":"selector","type":"bytes4"},{"internalType":"uint256","name":"accountOffset","type":"uint256"},{"internalType":"uint256","name":"returnOffset","type":"uint256"},{"internalType":"uint256","name":"actual","type":"uint256"},{"internalType":"uint256","name":"minimum","type":"uint256"}],"name":"StaticCallUint256BelowMinimum","type":"error"},{"inputs":[{"internalType":"address","name":"target","type":"address"},{"internalType":"bytes","name":"data","type":"bytes"},{"internalType":"uint32","name":"accountOffset","type":"uint32"},{"internalType":"uint32","name":"returnOffset","type":"uint32"},{"internalType":"uint256","name":"minimum","type":"uint256"}],"name":"assertStaticCallUint256AtLeast","outputs":[],"stateMutability":"view","type":"function"},{"inputs":[{"internalType":"address","name":"target","type":"address"},{"internalType":"bytes","name":"data","type":"bytes"},{"internalType":"uint32","name":"accountOffset","type":"uint32"},{"internalType":"uint32","name":"returnOffset","type":"uint32"},{"internalType":"uint256","name":"maximum","type":"uint256"}],"name":"assertStaticCallUint256AtMost","outputs":[],"stateMutability":"view","type":"function"}]
